pymfm/__init__.py
pymfm/control/__init__.py
pymfm/control/algorithms/__init__.py
pymfm/control/algorithms/optimization_based.py
pymfm/control/algorithms/rule_based.py
pymfm/control/utils/__init__.py
pymfm/control/utils/data_input.py
pymfm/control/utils/data_output.py
pymfm/control/utils/mode_logic_handler.py
pymfm/examples/__init__.py
pymfm/examples/control/__init__.py
pymfm/examples/control/near_real_time_rule_based.py
pymfm/examples/control/scheduling_optimization_based.py
pymfm/examples/control/scheduling_rule_based.py
pymfm/examples/scenario_forecast_kit/__init__.py
pymfm/examples/scenario_forecast_kit/forecast_and_scenario_generation.py
pymfm/scenario_forecast_kit/__init__.py
pymfm/scenario_forecast_kit/forecast_generation.py
pymfm/scenario_forecast_kit/scenario_generation.py
pymfm-0.5.5.dist-info/LICENSE
pymfm-0.5.5.dist-info/METADATA
pymfm-0.5.5.dist-info/WHEEL
pymfm-0.5.5.dist-info/top_level.txt
pymfm-0.5.5.dist-info/RECORD
