Metadata-Version: 2.1
Name: pymfm
Version: 0.5.5
Summary: A Python framework for microgrid flexibility management.
Author-email: "Institute for Automation of Complex Power Systems (ACS), E.ON Energy Research Center (E.ON ERC), RWTH Aachen University" <post_acs@eonerc.rwth-aachen.de>
License: Apache-2.0
Platform: any
Classifier: Development Status :: 5 - Production/Stable
Classifier: Operating System :: OS Independent
Classifier: Intended Audience :: Science/Research
Classifier: License :: OSI Approved :: Apache Software License
Classifier: Topic :: Scientific/Engineering
Classifier: Natural Language :: English
Classifier: Programming Language :: Python :: 3.8
Requires-Python: >=3.8
License-File: LICENSE
Requires-Dist: pandas ==1.5.3
Requires-Dist: pyomo ==6.5.0
Requires-Dist: matplotlib ==3.7.1
Requires-Dist: scipy ==1.11.0
Requires-Dist: xlsxwriter ==3.1.2
Requires-Dist: pydantic ==1.10.9
Requires-Dist: astral ==3.2
